[{"﻿Kutu Adı":"T01-0001","IMEI":"3.58021E+14","Olay Kodları":"Bağlantı Yenilendi","Pil":"0.55","Zaman":"07.07.2019 23:55:35","Enlem":"39.90777","Boylam":"32.88257","Hata":"0","Kaynak":"GPS","Rakım":"917","Son Adres Bilgisi ":"244. Cd. Aşıkpaşa Merkez Ankara / Türkiye     "},{"﻿Kutu Adı":"T01-0001","IMEI":"3.58021E+14","Olay Kodları":"Bağlantı Yenilendi","Pil":"0.6","Zaman":"07.07.2019 22:54:15","Enlem":"39.90764","Boylam":"32.88252","Hata":"0","Kaynak":"GPS","Rakım":"924","Son Adres Bilgisi ":"Vedat Dalokay Cd. Aşıkpaşa Merkez Ankara / Türkiye     "},{"﻿Kutu Adı":"T01-0001","IMEI":"3.58021E+14","Olay Kodları":"Bağlantı Yenilendi","Pil":"0.55","Zaman":"07.07.2019 21:52:29","Enlem":"39.90766","Boylam":"32.88263","Hata":"0","Kaynak":"GPS","Rakım":"940","Son Adres Bilgisi ":"244. Cd. Aşıkpaşa Merkez Ankara / Türkiye     "},{"﻿Kutu Adı":"T01-0001","IMEI":"3.58021E+14","Olay Kodları":"Bağlantı Yenilendi","Pil":"0.6","Zaman":"07.07.2019 20:50:23","Enlem":"39.9077","Boylam":"32.88251","Hata":"0","Kaynak":"GPS","Rakım":"924","Son Adres Bilgisi ":"Vedat Dalokay Cd. Aşıkpaşa Merkez Ankara / Türkiye     "},{"﻿Kutu Adı":"T01-0001","IMEI":"3.58021E+14","Olay Kodları":"Bağlantı Yenilendi","Pil":"0.6","Zaman":"07.07.2019 19:45:05","Enlem":"39.9306","Boylam":"32.82311","Hata":"0","Kaynak":"GPS","Rakım":"842","Son Adres Bilgisi ":"Kazakistan Cd. Bahçelievler Merkez Ankara / Türkiye     "},{"﻿Kutu Adı":"T01-0001","IMEI":"3.58021E+14","Olay Kodları":"Bağlantı Yenilendi","Pil":"0.6","Zaman":"07.07.2019 18:41:17","Enlem":"39.92261","Boylam":"32.82183","Hata":"0","Kaynak":"GPS","Rakım":"906","Son Adres Bilgisi ":"Veli Necdet Arığ Cd. Yukarı Bahçelievler Merkez Ankara / Türkiye     "},{"﻿Kutu Adı":"T01-0001","IMEI":"3.58021E+14","Olay Kodları":"Bağlantı Yenilendi","Pil":"0.6","Zaman":"07.07.2019 17:39:15","Enlem":"39.92243","Boylam":"32.82216","Hata":"0","Kaynak":"GPS","Rakım":"927","Son Adres Bilgisi ":"Veli Necdet Arığ Cd. Yukarı Bahçelievler Merkez Ankara / Türkiye     "},{"﻿Kutu Adı":"T01-0001","IMEI":"3.58021E+14","Olay Kodları":"Bağlantı Yenilendi","Pil":"0.6","Zaman":"07.07.2019 16:35:43","Enlem":"39.92907248","Boylam":"32.8233672","Hata":"155","Kaynak":"WIFI","Rakım":"0","Son Adres Bilgisi ":"Kazakistan Cd. Bahçelievler Merkez Ankara / Türkiye     "},{"﻿Kutu Adı":"T01-0001","IMEI":"3.58021E+14","Olay Kodları":"Bağlantı Yenilendi","Pil":"0.6","Zaman":"07.07.2019 14:49:53","Enlem":"39.89771415","Boylam":"32.87877338","Hata":"130","Kaynak":"WIFI","Rakım":"0","Son Adres Bilgisi ":"Kaptanpaşa Cd. Büyükesat Merkez Ankara / Türkiye     "},{"﻿Kutu Adı":"T01-0001","IMEI":"3.58021E+14","Olay Kodları":"Bağlantı Yenilendi","Pil":"0.6","Zaman":"07.07.2019 13:47:48","Enlem":"39.90759","Boylam":"32.88245","Hata":"0","Kaynak":"GPS","Rakım":"915","Son Adres Bilgisi ":"Vedat Dalokay Cd. Aşıkpaşa Merkez Ankara / Türkiye     "},{"﻿Kutu Adı":"T01-0001","IMEI":"3.58021E+14","Olay Kodları":"Bağlantı Yenilendi","Pil":"0.6","Zaman":"07.07.2019 12:46:45","Enlem":"39.90766","Boylam":"32.88246","Hata":"0","Kaynak":"GPS","Rakım":"946","Son Adres Bilgisi ":"Vedat Dalokay Cd. Aşıkpaşa Merkez Ankara / Türkiye     "},{"﻿Kutu Adı":"T01-0001","IMEI":"3.58021E+14","Olay Kodları":"Bağlantı Yenilendi","Pil":"0.6","Zaman":"07.07.2019 11:45:45","Enlem":"39.9077","Boylam":"32.88237","Hata":"0","Kaynak":"GPS","Rakım":"940","Son Adres Bilgisi ":"Vedat Dalokay Cd. Aşıkpaşa Merkez Ankara / Türkiye     "},{"﻿Kutu Adı":"T01-0001","IMEI":"3.58021E+14","Olay Kodları":"Bağlantı Yenilendi","Pil":"0.6","Zaman":"07.07.2019 10:42:59","Enlem":"39.90749","Boylam":"32.88247","Hata":"0","Kaynak":"GPS","Rakım":"912","Son Adres Bilgisi ":"Vedat Dalokay Cd. Aşıkpaşa Merkez Ankara / Türkiye     "},{"﻿Kutu Adı":"T01-0001","IMEI":"3.58021E+14","Olay Kodları":"Bağlantı Yenilendi","Pil":"0.6","Zaman":"07.07.2019 09:40:48","Enlem":"39.90776","Boylam":"32.88247","Hata":"0","Kaynak":"GPS","Rakım":"946","Son Adres Bilgisi ":"Vedat Dalokay Cd. Aşıkpaşa Merkez Ankara / Türkiye     "},{"﻿Kutu Adı":"T01-0001","IMEI":"3.58021E+14","Olay Kodları":"Bağlantı Yenilendi","Pil":"0.6","Zaman":"07.07.2019 08:36:46","Enlem":"39.90785","Boylam":"32.88257","Hata":"0","Kaynak":"GPS","Rakım":"926","Son Adres Bilgisi ":"244. Cd. Aşıkpaşa Merkez Ankara / Türkiye     "},{"﻿Kutu Adı":"T01-0001","IMEI":"3.58021E+14","Olay Kodları":"Bağlantı Yenilendi","Pil":"0.6","Zaman":"07.07.2019 07:30:05","Enlem":"39.90763507","Boylam":"32.88258836","Hata":"150","Kaynak":"WIFI","Rakım":"0","Son Adres Bilgisi ":"Vedat Dalokay Cd. Aşıkpaşa Merkez Ankara / Türkiye     "},{"﻿Kutu Adı":"T01-0001","IMEI":"3.58021E+14","Olay Kodları":"Bağlantı Yenilendi","Pil":"0.6","Zaman":"07.07.2019 06:27:46","Enlem":"39.90763","Boylam":"32.88253","Hata":"0","Kaynak":"GPS","Rakım":"930","Son Adres Bilgisi ":"Vedat Dalokay Cd. Aşıkpaşa Merkez Ankara / Türkiye     "},{"﻿Kutu Adı":"T01-0001","IMEI":"3.58021E+14","Olay Kodları":"Bağlantı Yenilendi","Pil":"0.6","Zaman":"07.07.2019 05:25:14","Enlem":"39.90797","Boylam":"32.88242","Hata":"0","Kaynak":"GPS","Rakım":"981","Son Adres Bilgisi ":"Vedat Dalokay Cd. Aşıkpaşa Merkez Ankara / Türkiye     "},{"﻿Kutu Adı":"T01-0001","IMEI":"3.58021E+14","Olay Kodları":"Bağlantı Yenilendi","Pil":"0.6","Zaman":"07.07.2019 04:24:16","Enlem":"39.9077","Boylam":"32.88238","Hata":"0","Kaynak":"GPS","Rakım":"955","Son Adres Bilgisi ":"Vedat Dalokay Cd. Aşıkpaşa Merkez Ankara / Türkiye     "},{"﻿Kutu Adı":"T01-0001","IMEI":"3.58021E+14","Olay Kodları":"Bağlantı Yenilendi","Pil":"0.6","Zaman":"07.07.2019 03:21:33","Enlem":"39.90762568","Boylam":"32.88257272","Hata":"140","Kaynak":"WIFI","Rakım":"0","Son Adres Bilgisi ":"Vedat Dalokay Cd. Aşıkpaşa Merkez Ankara / Türkiye     "},{"﻿Kutu Adı":"T01-0001","IMEI":"3.58021E+14","Olay Kodları":"Bağlantı Yenilendi","Pil":"0.6","Zaman":"07.07.2019 02:18:29","Enlem":"39.90756","Boylam":"32.88254","Hata":"0","Kaynak":"GPS","Rakım":"905","Son Adres Bilgisi ":"Vedat Dalokay Cd. Aşıkpaşa Merkez Ankara / Türkiye     "},{"﻿Kutu Adı":"T01-0001","IMEI":"3.58021E+14","Olay Kodları":"Bağlantı Yenilendi","Pil":"0.6","Zaman":"07.07.2019 01:16:05","Enlem":"39.90696","Boylam":"32.88302","Hata":"0","Kaynak":"GPS","Rakım":"926","Son Adres Bilgisi ":"Açın Cd. Aşıkpaşa Merkez Ankara / Türkiye     "},{"﻿Kutu Adı":"T01-0001","IMEI":"3.58021E+14","Olay Kodları":"Bağlantı Yenilendi","Pil":"0.6","Zaman":"07.07.2019 00:12:05","Enlem":"39.90756","Boylam":"32.8825","Hata":"0","Kaynak":"GPS","Rakım":"931","Son Adres Bilgisi ":"Vedat Dalokay Cd. Aşıkpaşa Merkez Ankara / Türkiye     "},{"﻿Kutu Adı":"T01-0001","IMEI":"3.58021E+14","Olay Kodları":"Bağlantı Yenilendi","Pil":"0.6","Zaman":"06.07.2019 23:07:39","Enlem":"39.90448","Boylam":"32.88895","Hata":"0","Kaynak":"GPS","Rakım":"111","Son Adres Bilgisi ":"237. Sk. Boztepe Merkez Ankara / Türkiye     "},{"﻿Kutu Adı":"T01-0001","IMEI":"3.58021E+14","Olay Kodları":"Bağlantı Yenilendi","Pil":"0.6","Zaman":"06.07.2019 22:05:53","Enlem":"39.90735","Boylam":"32.88269","Hata":"0","Kaynak":"GPS","Rakım":"951","Son Adres Bilgisi ":"Açın Cd. Aşıkpaşa Merkez Ankara / Türkiye     "},{"﻿Kutu Adı":"T01-0001","IMEI":"3.58021E+14","Olay Kodları":"Bağlantı Yenilendi","Pil":"0.6","Zaman":"06.07.2019 20:59:22","Enlem":"40.13217","Boylam":"32.60013","Hata":"0","Kaynak":"GPS","Rakım":"771","Son Adres Bilgisi ":"Anadolu Otoyolu Karalar Merkez Ankara / Türkiye     "},{"﻿Kutu Adı":"T01-0001","IMEI":"3.58021E+14","Olay Kodları":"Bağlantı Yenilendi","Pil":"0.6","Zaman":"06.07.2019 19:46:29","Enlem":"40.75177","Boylam":"31.7767","Hata":"0","Kaynak":"GPS","Rakım":"594","Son Adres Bilgisi ":"Anadolu Otoyolu Yeniçaydurt Yeniçaydurt Bolu / Türkiye     "},{"﻿Kutu Adı":"T01-0001","IMEI":"3.58021E+14","Olay Kodları":"Bağlantı Yenilendi","Pil":"0.6","Zaman":"06.07.2019 18:45:10","Enlem":"40.73180542","Boylam":"31.60896296","Hata":"155","Kaynak":"WIFI","Rakım":"0","Son Adres Bilgisi ":"Öney Sk. Aktaş Merkez Bolu / Türkiye     "},{"﻿Kutu Adı":"T01-0001","IMEI":"3.58021E+14","Olay Kodları":"Bağlantı Yenilendi","Pil":"0.6","Zaman":"06.07.2019 17:20:21","Enlem":"40.88395","Boylam":"31.68286","Hata":"0","Kaynak":"GPS","Rakım":"1686","Son Adres Bilgisi ":"Yedigöller Yolu Yeşilçele Yeşilçele Bolu / Türkiye     "},{"﻿Kutu Adı":"T01-0001","IMEI":"3.58021E+14","Olay Kodları":"Bağlantı Yenilendi","Pil":"0.6","Zaman":"06.07.2019 16:17:45","Enlem":"40.94212","Boylam":"31.74658","Hata":"0","Kaynak":"GPS","Rakım":"808","Son Adres Bilgisi ":"Yedigöller Yolu Bağışlar Bağışlar Bolu / Türkiye     "},{"﻿Kutu Adı":"T01-0001","IMEI":"3.58021E+14","Olay Kodları":"Bağlantı Yenilendi","Pil":"0.6","Zaman":"06.07.2019 14:47:47","Enlem":"40.87478","Boylam":"31.69026","Hata":"0","Kaynak":"GPS","Rakım":"1700","Son Adres Bilgisi ":"Yedigöller Yolu Yeşilçele Yeşilçele Bolu / Türkiye     "},{"﻿Kutu Adı":"T01-0001","IMEI":"3.58021E+14","Olay Kodları":"Bağlantı Yenilendi","Pil":"0.6","Zaman":"06.07.2019 13:41:48","Enlem":"40.65711","Boylam":"31.62926","Hata":"0","Kaynak":"GPS","Rakım":"0","Son Adres Bilgisi ":"Gölcük Milli Parkı Mesciler Mesciler Bolu / Türkiye     "},{"﻿Kutu Adı":"T01-0001","IMEI":"3.58021E+14","Olay Kodları":"Bağlantı Yenilendi","Pil":"0.65","Zaman":"06.07.2019 12:41:29","Enlem":"40.65687","Boylam":"31.62921","Hata":"0","Kaynak":"GPS","Rakım":"1181","Son Adres Bilgisi ":"Gölcük Milli Parkı Mesciler Mesciler Bolu / Türkiye     "},{"﻿Kutu Adı":"T01-0001","IMEI":"3.58021E+14","Olay Kodları":"Bağlantı Yenilendi","Pil":"0.6","Zaman":"06.07.2019 11:39:36","Enlem":"40.65688","Boylam":"31.62925","Hata":"0","Kaynak":"GPS","Rakım":"1203","Son Adres Bilgisi ":"Gölcük Milli Parkı Mesciler Mesciler Bolu / Türkiye     "},{"﻿Kutu Adı":"T01-0001","IMEI":"3.58021E+14","Olay Kodları":"Bağlantı Yenilendi","Pil":"0.65","Zaman":"06.07.2019 09:26:00","Enlem":"39.90811191","Boylam":"32.88263491","Hata":"255","Kaynak":"WIFI","Rakım":"0","Son Adres Bilgisi ":"Vedat Dalokay Cd. Aşıkpaşa Merkez Ankara / Türkiye     "},{"﻿Kutu Adı":"T01-0001","IMEI":"3.58021E+14","Olay Kodları":"Bağlantı Yenilendi","Pil":"0.65","Zaman":"06.07.2019 08:22:33","Enlem":"39.90603372","Boylam":"32.88077957","Hata":"55","Kaynak":"WIFI","Rakım":"0","Son Adres Bilgisi ":"Vedat Dalokay Cd. Aşıkpaşa Merkez Ankara / Türkiye     "},{"﻿Kutu Adı":"T01-0001","IMEI":"3.58021E+14","Olay Kodları":"Bağlantı Yenilendi","Pil":"0.65","Zaman":"06.07.2019 07:19:05","Enlem":"39.90745","Boylam":"32.88288","Hata":"0","Kaynak":"GPS","Rakım":"975","Son Adres Bilgisi ":"Açın Cd. Aşıkpaşa Merkez Ankara / Türkiye     "},{"﻿Kutu Adı":"T01-0001","IMEI":"3.58021E+14","Olay Kodları":"Bağlantı Yenilendi","Pil":"0.65","Zaman":"06.07.2019 06:17:46","Enlem":"39.90772","Boylam":"32.88249","Hata":"0","Kaynak":"GPS","Rakım":"928","Son Adres Bilgisi ":"Vedat Dalokay Cd. Aşıkpaşa Merkez Ankara / Türkiye     "},{"﻿Kutu Adı":"T01-0001","IMEI":"3.58021E+14","Olay Kodları":"Bağlantı Yenilendi","Pil":"0.65","Zaman":"06.07.2019 05:14:35","Enlem":"39.90891","Boylam":"32.88094","Hata":"0","Kaynak":"GPS","Rakım":"133","Son Adres Bilgisi ":"220. Cd. Aşıkpaşa Merkez Ankara / Türkiye     "},{"﻿Kutu Adı":"T01-0001","IMEI":"3.58021E+14","Olay Kodları":"Bağlantı Yenilendi","Pil":"0.65","Zaman":"06.07.2019 04:13:15","Enlem":"39.90767","Boylam":"32.88246","Hata":"0","Kaynak":"GPS","Rakım":"926","Son Adres Bilgisi ":"Vedat Dalokay Cd. Aşıkpaşa Merkez Ankara / Türkiye     "},{"﻿Kutu Adı":"T01-0001","IMEI":"3.58021E+14","Olay Kodları":"Bağlantı Yenilendi","Pil":"0.65","Zaman":"06.07.2019 03:11:23","Enlem":"39.90762","Boylam":"32.88247","Hata":"0","Kaynak":"GPS","Rakım":"919","Son Adres Bilgisi ":"Vedat Dalokay Cd. Aşıkpaşa Merkez Ankara / Türkiye     "},{"﻿Kutu Adı":"T01-0001","IMEI":"3.58021E+14","Olay Kodları":"Bağlantı Yenilendi","Pil":"0.65","Zaman":"06.07.2019 02:10:17","Enlem":"39.90764","Boylam":"32.88244","Hata":"0","Kaynak":"GPS","Rakım":"919","Son Adres Bilgisi ":"Vedat Dalokay Cd. Aşıkpaşa Merkez Ankara / Türkiye     "},{"﻿Kutu Adı":"T01-0001","IMEI":"3.58021E+14","Olay Kodları":"Bağlantı Yenilendi","Pil":"0.65","Zaman":"06.07.2019 01:08:18","Enlem":"39.90757","Boylam":"32.88256","Hata":"0","Kaynak":"GPS","Rakım":"928","Son Adres Bilgisi ":"Vedat Dalokay Cd. Aşıkpaşa Merkez Ankara / Türkiye     "},{"﻿Kutu Adı":"T01-0001","IMEI":"3.58021E+14","Olay Kodları":"Bağlantı Yenilendi","Pil":"0.65","Zaman":"06.07.2019 00:06:24","Enlem":"39.90755","Boylam":"32.8826","Hata":"0","Kaynak":"GPS","Rakım":"916","Son Adres Bilgisi ":"Vedat Dalokay Cd. Aşıkpaşa Merkez Ankara / Türkiye     "},{"﻿Kutu Adı":"T01-0001","IMEI":"3.58021E+14","Olay Kodları":"Bağlantı Yenilendi","Pil":"0.65","Zaman":"05.07.2019 23:04:16","Enlem":"39.90761","Boylam":"32.88256","Hata":"0","Kaynak":"GPS","Rakım":"925","Son Adres Bilgisi ":"Vedat Dalokay Cd. Aşıkpaşa Merkez Ankara / Türkiye     "},{"﻿Kutu Adı":"T01-0001","IMEI":"3.58021E+14","Olay Kodları":"Bağlantı Yenilendi","Pil":"0.65","Zaman":"05.07.2019 22:03:35","Enlem":"39.90748","Boylam":"32.8826","Hata":"0","Kaynak":"GPS","Rakım":"934","Son Adres Bilgisi ":"Vedat Dalokay Cd. Aşıkpaşa Merkez Ankara / Türkiye     "},{"﻿Kutu Adı":"T01-0001","IMEI":"3.58021E+14","Olay Kodları":"Bağlantı Yenilendi","Pil":"0.7","Zaman":"05.07.2019 21:01:58","Enlem":"39.90763","Boylam":"32.88247","Hata":"0","Kaynak":"GPS","Rakım":"903","Son Adres Bilgisi ":"Vedat Dalokay Cd. Aşıkpaşa Merkez Ankara / Türkiye     "},{"﻿Kutu Adı":"T01-0001","IMEI":"3.58021E+14","Olay Kodları":"Bağlantı Yenilendi","Pil":"0.7","Zaman":"05.07.2019 20:01:15","Enlem":"39.90748","Boylam":"32.88266","Hata":"0","Kaynak":"GPS","Rakım":"907","Son Adres Bilgisi ":"244. Cd. Aşıkpaşa Merkez Ankara / Türkiye     "},{"﻿Kutu Adı":"T01-0001","IMEI":"3.58021E+14","Olay Kodları":"Bağlantı Yenilendi","Pil":"0.7","Zaman":"05.07.2019 18:59:21","Enlem":"39.9063394","Boylam":"32.8576627","Hata":"60","Kaynak":"WIFI","Rakım":"0","Son Adres Bilgisi ":"Kuğulu-2 Altgeçidi Remzi Oğuz Arık Merkez Ankara / Türkiye     "},{"﻿Kutu Adı":"T01-0001","IMEI":"3.58021E+14","Olay Kodları":"Bağlantı Yenilendi","Pil":"0.7","Zaman":"05.07.2019 17:57:48","Enlem":"39.87973","Boylam":"32.86152","Hata":"0","Kaynak":"GPS","Rakım":"1080","Son Adres Bilgisi ":"Simon Bolivar Blv. Çankaya Merkez Ankara / Türkiye     "},{"﻿Kutu Adı":"T01-0001","IMEI":"3.58021E+14","Olay Kodları":"Bağlantı Yenilendi","Pil":"0.7","Zaman":"05.07.2019 16:54:21","Enlem":"39.8755821","Boylam":"32.86374206","Hata":"145","Kaynak":"WIFI","Rakım":"0","Son Adres Bilgisi ":"Turan Güneş Blv. Sancak Merkez Ankara / Türkiye     "},{"﻿Kutu Adı":"T01-0001","IMEI":"3.58021E+14","Olay Kodları":"Bağlantı Yenilendi","Pil":"0.7","Zaman":"05.07.2019 15:53:07","Enlem":"39.87570147","Boylam":"32.86393244","Hata":"145","Kaynak":"WIFI","Rakım":"0","Son Adres Bilgisi ":"508. Cd. Sancak Merkez Ankara / Türkiye     "},{"﻿Kutu Adı":"T01-0001","IMEI":"3.58021E+14","Olay Kodları":"Bağlantı Yenilendi","Pil":"0.7","Zaman":"05.07.2019 14:51:49","Enlem":"39.87560925","Boylam":"32.86404166","Hata":"145","Kaynak":"WIFI","Rakım":"0","Son Adres Bilgisi ":"507. Sk. Sancak Merkez Ankara / Türkiye     "},{"﻿Kutu Adı":"T01-0001","IMEI":"3.58021E+14","Olay Kodları":"Bağlantı Yenilendi","Pil":"0.7","Zaman":"05.07.2019 13:50:14","Enlem":"39.87569762","Boylam":"32.86393754","Hata":"145","Kaynak":"WIFI","Rakım":"0","Son Adres Bilgisi ":"508. Cd. Sancak Merkez Ankara / Türkiye     "},{"﻿Kutu Adı":"T01-0001","IMEI":"3.58021E+14","Olay Kodları":"Bağlantı Yenilendi","Pil":"0.7","Zaman":"05.07.2019 12:49:07","Enlem":"39.87566728","Boylam":"32.86385048","Hata":"145","Kaynak":"WIFI","Rakım":"0","Son Adres Bilgisi ":"508. Cd. Sancak Merkez Ankara / Türkiye     "},{"﻿Kutu Adı":"T01-0001","IMEI":"3.58021E+14","Olay Kodları":"Bağlantı Yenilendi","Pil":"0.65","Zaman":"05.07.2019 11:41:28","Enlem":"39.87585467","Boylam":"32.86391548","Hata":"145","Kaynak":"WIFI","Rakım":"0","Son Adres Bilgisi ":"508. Cd. Sancak Merkez Ankara / Türkiye     "},{"﻿Kutu Adı":"T01-0001","IMEI":"3.58021E+14","Olay Kodları":"Bağlantı Yenilendi","Pil":"0.65","Zaman":"05.07.2019 10:41:25","Enlem":"39.87541","Boylam":"32.86416","Hata":"0","Kaynak":"GPS","Rakım":"1052","Son Adres Bilgisi ":"507. Sk. Sancak Merkez Ankara / Türkiye     "},{"﻿Kutu Adı":"T01-0001","IMEI":"3.58021E+14","Olay Kodları":"Bağlantı Yenilendi","Pil":"0.65","Zaman":"05.07.2019 09:35:05","Enlem":"39.87562","Boylam":"32.86337","Hata":"0","Kaynak":"GPS","Rakım":"1143","Son Adres Bilgisi ":"Turan Güneş Blv. Yıldızevler Merkez Ankara / Türkiye     "},{"﻿Kutu Adı":"T01-0001","IMEI":"3.58021E+14","Olay Kodları":"Bağlantı Yenilendi","Pil":"0.65","Zaman":"05.07.2019 08:28:55","Enlem":"39.87576777","Boylam":"32.86314227","Hata":"145","Kaynak":"WIFI","Rakım":"0","Son Adres Bilgisi ":"Turan Güneş Blv. Yıldızevler Merkez Ankara / Türkiye     "},{"﻿Kutu Adı":"T01-0001","IMEI":"3.58021E+14","Olay Kodları":"Bağlantı Yenilendi","Pil":"0.65","Zaman":"05.07.2019 07:28:46","Enlem":"39.90769475","Boylam":"32.88252899","Hata":"125","Kaynak":"WIFI","Rakım":"0","Son Adres Bilgisi ":"Vedat Dalokay Cd. Aşıkpaşa Merkez Ankara / Türkiye     "},{"﻿Kutu Adı":"T01-0001","IMEI":"3.58021E+14","Olay Kodları":"Bağlantı Yenilendi","Pil":"0.65","Zaman":"05.07.2019 06:25:19","Enlem":"39.90972","Boylam":"32.88187","Hata":"0","Kaynak":"GPS","Rakım":"111","Son Adres Bilgisi ":"222. Sk. Aşıkpaşa Merkez Ankara / Türkiye     "},{"﻿Kutu Adı":"T01-0001","IMEI":"3.58021E+14","Olay Kodları":"Bağlantı Yenilendi","Pil":"0.65","Zaman":"05.07.2019 05:22:47","Enlem":"39.90747","Boylam":"32.88254","Hata":"0","Kaynak":"GPS","Rakım":"939","Son Adres Bilgisi ":"Vedat Dalokay Cd. Aşıkpaşa Merkez Ankara / Türkiye     "},{"﻿Kutu Adı":"T01-0001","IMEI":"3.58021E+14","Olay Kodları":"Bağlantı Yenilendi","Pil":"0.65","Zaman":"05.07.2019 04:21:18","Enlem":"39.90595","Boylam":"32.88764","Hata":"0","Kaynak":"GPS","Rakım":"111","Son Adres Bilgisi ":"234. Sk. Boztepe Merkez Ankara / Türkiye     "},{"﻿Kutu Adı":"T01-0001","IMEI":"3.58021E+14","Olay Kodları":"Bağlantı Yenilendi","Pil":"0.65","Zaman":"05.07.2019 03:19:15","Enlem":"39.90769","Boylam":"32.88206","Hata":"0","Kaynak":"GPS","Rakım":"0","Son Adres Bilgisi ":"215. Sk. Aşıkpaşa Merkez Ankara / Türkiye     "},{"﻿Kutu Adı":"T01-0001","IMEI":"3.58021E+14","Olay Kodları":"Bağlantı Yenilendi","Pil":"0.7","Zaman":"05.07.2019 02:18:05","Enlem":"39.90768","Boylam":"32.88246","Hata":"0","Kaynak":"GPS","Rakım":"926","Son Adres Bilgisi ":"Vedat Dalokay Cd. Aşıkpaşa Merkez Ankara / Türkiye     "},{"﻿Kutu Adı":"T01-0001","IMEI":"3.58021E+14","Olay Kodları":"Bağlantı Yenilendi","Pil":"0.7","Zaman":"05.07.2019 01:14:49","Enlem":"39.89757","Boylam":"32.87991","Hata":"0","Kaynak":"GPS","Rakım":"112","Son Adres Bilgisi ":"Açın Cd. Büyükesat Merkez Ankara / Türkiye     "},{"﻿Kutu Adı":"T01-0001","IMEI":"3.58021E+14","Olay Kodları":"Bağlantı Yenilendi","Pil":"0.7","Zaman":"05.07.2019 00:12:45","Enlem":"39.90771","Boylam":"32.88246","Hata":"0","Kaynak":"GPS","Rakım":"956","Son Adres Bilgisi ":"Vedat Dalokay Cd. Aşıkpaşa Merkez Ankara / Türkiye     "},{"﻿Kutu Adı":"T01-0001","IMEI":"3.58021E+14","Olay Kodları":"Bağlantı Yenilendi","Pil":"0.7","Zaman":"04.07.2019 23:09:30","Enlem":"39.90887","Boylam":"32.88162","Hata":"0","Kaynak":"GPS","Rakım":"156","Son Adres Bilgisi ":"216. Sk. Aşıkpaşa Merkez Ankara / Türkiye     "},{"﻿Kutu Adı":"T01-0001","IMEI":"3.58021E+14","Olay Kodları":"Bağlantı Yenilendi","Pil":"0.7","Zaman":"04.07.2019 22:07:02","Enlem":"39.90741","Boylam":"32.88259","Hata":"0","Kaynak":"GPS","Rakım":"922","Son Adres Bilgisi ":"Vedat Dalokay Cd. Aşıkpaşa Merkez Ankara / Türkiye     "},{"﻿Kutu Adı":"T01-0001","IMEI":"3.58021E+14","Olay Kodları":"Bağlantı Yenilendi","Pil":"0.7","Zaman":"04.07.2019 21:06:00","Enlem":"39.90772","Boylam":"32.88234","Hata":"0","Kaynak":"GPS","Rakım":"867","Son Adres Bilgisi ":"Vedat Dalokay Cd. Aşıkpaşa Merkez Ankara / Türkiye     "},{"﻿Kutu Adı":"T01-0001","IMEI":"3.58021E+14","Olay Kodları":"Bağlantı Yenilendi","Pil":"0.7","Zaman":"04.07.2019 20:04:47","Enlem":"39.90759","Boylam":"32.88261","Hata":"0","Kaynak":"GPS","Rakım":"934","Son Adres Bilgisi ":"244. Cd. Aşıkpaşa Merkez Ankara / Türkiye     "},{"﻿Kutu Adı":"T01-0001","IMEI":"3.58021E+14","Olay Kodları":"Bağlantı Yenilendi","Pil":"0.7","Zaman":"04.07.2019 19:03:36","Enlem":"39.90788","Boylam":"32.88147","Hata":"0","Kaynak":"GPS","Rakım":"1026","Son Adres Bilgisi ":"214. Cd. Aşıkpaşa Merkez Ankara / Türkiye     "},{"﻿Kutu Adı":"T01-0001","IMEI":"3.58021E+14","Olay Kodları":"Bağlantı Yenilendi","Pil":"0.7","Zaman":"04.07.2019 18:01:01","Enlem":"39.90764","Boylam":"32.88248","Hata":"0","Kaynak":"GPS","Rakım":"934","Son Adres Bilgisi ":"Vedat Dalokay Cd. Aşıkpaşa Merkez Ankara / Türkiye     "},{"﻿Kutu Adı":"T01-0001","IMEI":"3.58021E+14","Olay Kodları":"Bağlantı Yenilendi","Pil":"0.75","Zaman":"04.07.2019 16:48:50","Enlem":"39.87557257","Boylam":"32.86390312","Hata":"145","Kaynak":"WIFI","Rakım":"0","Son Adres Bilgisi ":"507. Sk. Sancak Merkez Ankara / Türkiye     "},{"﻿Kutu Adı":"T01-0001","IMEI":"3.58021E+14","Olay Kodları":"Bağlantı Yenilendi","Pil":"0.7","Zaman":"04.07.2019 15:47:36","Enlem":"39.87568966","Boylam":"32.86395482","Hata":"145","Kaynak":"WIFI","Rakım":"0","Son Adres Bilgisi ":"508. Cd. Sancak Merkez Ankara / Türkiye     "},{"﻿Kutu Adı":"T01-0001","IMEI":"3.58021E+14","Olay Kodları":"Bağlantı Yenilendi","Pil":"0.65","Zaman":"04.07.2019 14:39:38","Enlem":"39.87573036","Boylam":"32.86384635","Hata":"145","Kaynak":"WIFI","Rakım":"0","Son Adres Bilgisi ":"508. Cd. Sancak Merkez Ankara / Türkiye     "},{"﻿Kutu Adı":"T01-0001","IMEI":"3.58021E+14","Olay Kodları":"Bağlantı Yenilendi","Pil":"0.65","Zaman":"04.07.2019 13:39:01","Enlem":"39.87572344","Boylam":"32.86378273","Hata":"145","Kaynak":"WIFI","Rakım":"0","Son Adres Bilgisi ":"508. Cd. Sancak Merkez Ankara / Türkiye     "},{"﻿Kutu Adı":"T01-0001","IMEI":"3.58021E+14","Olay Kodları":"Bağlantı Yenilendi","Pil":"0.6","Zaman":"04.07.2019 12:37:34","Enlem":"39.87564034","Boylam":"32.86375723","Hata":"145","Kaynak":"WIFI","Rakım":"0","Son Adres Bilgisi ":"508. Cd. Sancak Merkez Ankara / Türkiye     "},{"﻿Kutu Adı":"T01-0001","IMEI":"3.58021E+14","Olay Kodları":"Bağlantı Yenilendi","Pil":"0.6","Zaman":"04.07.2019 11:29:43","Enlem":"39.87578118","Boylam":"32.86375282","Hata":"145","Kaynak":"WIFI","Rakım":"0","Son Adres Bilgisi ":"508. Cd. Sancak Merkez Ankara / Türkiye     "},{"﻿Kutu Adı":"T01-0001","IMEI":"3.58021E+14","Olay Kodları":"Bağlantı Yenilendi","Pil":"0.5","Zaman":"04.07.2019 10:28:36","Enlem":"39.87577364","Boylam":"32.86333766","Hata":"145","Kaynak":"WIFI","Rakım":"0","Son Adres Bilgisi ":"Turan Güneş Blv. Yıldızevler Merkez Ankara / Türkiye     "},{"﻿Kutu Adı":"T01-0001","IMEI":"3.58021E+14","Olay Kodları":"Bağlantı Yenilendi","Pil":"0.5","Zaman":"04.07.2019 09:24:05","Enlem":"39.87562","Boylam":"32.86389","Hata":"0","Kaynak":"GPS","Rakım":"1087","Son Adres Bilgisi ":"507. Sk. Sancak Merkez Ankara / Türkiye     "},{"﻿Kutu Adı":"T01-0001","IMEI":"3.58021E+14","Olay Kodları":"Bağlantı Yenilendi","Pil":"0.5","Zaman":"04.07.2019 08:19:35","Enlem":"39.88278641","Boylam":"32.87728521","Hata":"155","Kaynak":"WIFI","Rakım":"0","Son Adres Bilgisi ":"393. Cd. Birlik Merkez Ankara / Türkiye     "},{"﻿Kutu Adı":"T01-0001","IMEI":"3.58021E+14","Olay Kodları":"Bağlantı Yenilendi","Pil":"0.5","Zaman":"04.07.2019 07:15:48","Enlem":"39.9072","Boylam":"32.88293","Hata":"0","Kaynak":"GPS","Rakım":"1018","Son Adres Bilgisi ":"Açın Cd. Aşıkpaşa Merkez Ankara / Türkiye     "},{"﻿Kutu Adı":"T01-0001","IMEI":"3.58021E+14","Olay Kodları":"Bağlantı Yenilendi","Pil":"0.5","Zaman":"04.07.2019 06:14:52","Enlem":"39.90772","Boylam":"32.88269","Hata":"0","Kaynak":"GPS","Rakım":"904","Son Adres Bilgisi ":"244. Cd. Aşıkpaşa Merkez Ankara / Türkiye     "},{"﻿Kutu Adı":"T01-0001","IMEI":"3.58021E+14","Olay Kodları":"Bağlantı Yenilendi","Pil":"0.5","Zaman":"04.07.2019 05:13:35","Enlem":"39.90764","Boylam":"32.88258","Hata":"0","Kaynak":"GPS","Rakım":"923","Son Adres Bilgisi ":"Vedat Dalokay Cd. Aşıkpaşa Merkez Ankara / Türkiye     "},{"﻿Kutu Adı":"T01-0001","IMEI":"3.58021E+14","Olay Kodları":"Bağlantı Yenilendi","Pil":"0.5","Zaman":"04.07.2019 04:11:46","Enlem":"39.90794","Boylam":"32.88227","Hata":"0","Kaynak":"GPS","Rakım":"923","Son Adres Bilgisi ":"Vedat Dalokay Cd. Aşıkpaşa Merkez Ankara / Türkiye     "},{"﻿Kutu Adı":"T01-0001","IMEI":"3.58021E+14","Olay Kodları":"Bağlantı Yenilendi","Pil":"0.5","Zaman":"04.07.2019 03:08:48","Enlem":"39.90753","Boylam":"32.88253","Hata":"0","Kaynak":"GPS","Rakım":"941","Son Adres Bilgisi ":"Vedat Dalokay Cd. Aşıkpaşa Merkez Ankara / Türkiye     "},{"﻿Kutu Adı":"T01-0001","IMEI":"3.58021E+14","Olay Kodları":"Bağlantı Yenilendi","Pil":"0.5","Zaman":"04.07.2019 02:08:17","Enlem":"39.90746","Boylam":"32.88265","Hata":"0","Kaynak":"GPS","Rakım":"925","Son Adres Bilgisi ":"244. Cd. Aşıkpaşa Merkez Ankara / Türkiye     "},{"﻿Kutu Adı":"T01-0001","IMEI":"3.58021E+14","Olay Kodları":"Bağlantı Yenilendi","Pil":"0.5","Zaman":"04.07.2019 01:05:05","Enlem":"39.90758","Boylam":"32.88241","Hata":"0","Kaynak":"GPS","Rakım":"932","Son Adres Bilgisi ":"Vedat Dalokay Cd. Aşıkpaşa Merkez Ankara / Türkiye     "},{"﻿Kutu Adı":"T01-0001","IMEI":"3.58021E+14","Olay Kodları":"Bağlantı Yenilendi","Pil":"0.5","Zaman":"04.07.2019 00:01:35","Enlem":"39.90743","Boylam":"32.88225","Hata":"0","Kaynak":"GPS","Rakım":"956","Son Adres Bilgisi ":"Vedat Dalokay Cd. Aşıkpaşa Merkez Ankara / Türkiye     "},{"﻿Kutu Adı":"T01-0001","IMEI":"3.58021E+14","Olay Kodları":"Bağlantı Yenilendi","Pil":"0.5","Zaman":"03.07.2019 22:58:44","Enlem":"39.90774","Boylam":"32.88237","Hata":"0","Kaynak":"GPS","Rakım":"881","Son Adres Bilgisi ":"Vedat Dalokay Cd. Aşıkpaşa Merkez Ankara / Türkiye     "},{"﻿Kutu Adı":"T01-0001","IMEI":"3.58021E+14","Olay Kodları":"Bağlantı Yenilendi","Pil":"0.5","Zaman":"03.07.2019 21:57:47","Enlem":"39.90752","Boylam":"32.8825","Hata":"0","Kaynak":"GPS","Rakım":"933","Son Adres Bilgisi ":"Vedat Dalokay Cd. Aşıkpaşa Merkez Ankara / Türkiye     "},{"﻿Kutu Adı":"T01-0001","IMEI":"3.58021E+14","Olay Kodları":"Bağlantı Yenilendi","Pil":"0.5","Zaman":"03.07.2019 20:56:45","Enlem":"39.90769","Boylam":"32.88246","Hata":"0","Kaynak":"GPS","Rakım":"969","Son Adres Bilgisi ":"Vedat Dalokay Cd. Aşıkpaşa Merkez Ankara / Türkiye     "},{"﻿Kutu Adı":"T01-0001","IMEI":"3.58021E+14","Olay Kodları":"Bağlantı Yenilendi","Pil":"0.5","Zaman":"03.07.2019 19:52:39","Enlem":"39.9317846","Boylam":"32.84455863","Hata":"275","Kaynak":"WIFI","Rakım":"0","Son Adres Bilgisi ":"Ali Suavi Cd. Eti Merkez Ankara / Türkiye     "},{"﻿Kutu Adı":"T01-0001","IMEI":"3.58021E+14","Olay Kodları":"Bağlantı Yenilendi","Pil":"0.5","Zaman":"03.07.2019 18:46:30","Enlem":"39.93165435","Boylam":"32.84462258","Hata":"230","Kaynak":"WIFI","Rakım":"0","Son Adres Bilgisi ":"Ali Suavi Cd. Eti Merkez Ankara / Türkiye     "},{"﻿Kutu Adı":"T01-0001","IMEI":"3.58021E+14","Olay Kodları":"Bağlantı Yenilendi","Pil":"0.5","Zaman":"03.07.2019 17:45:24","Enlem":"39.87921","Boylam":"32.8603","Hata":"0","Kaynak":"GPS","Rakım":"1126","Son Adres Bilgisi ":"727. Sk. Yıldızevler Merkez Ankara / Türkiye     "},{"﻿Kutu Adı":"T01-0001","IMEI":"3.58021E+14","Olay Kodları":"Bağlantı Yenilendi","Pil":"0.5","Zaman":"03.07.2019 16:41:05","Enlem":"39.876","Boylam":"32.86389","Hata":"0","Kaynak":"GPS","Rakım":"1083","Son Adres Bilgisi ":"Turan Güneş Blv. Sancak Merkez Ankara / Türkiye     "},{"﻿Kutu Adı":"T01-0001","IMEI":"3.58021E+14","Olay Kodları":"Bağlantı Yenilendi","Pil":"0.5","Zaman":"03.07.2019 15:37:46","Enlem":"39.87573","Boylam":"32.86405","Hata":"0","Kaynak":"GPS","Rakım":"1132","Son Adres Bilgisi ":"508. Cd. Sancak Merkez Ankara / Türkiye     "},{"﻿Kutu Adı":"T01-0001","IMEI":"3.58021E+14","Olay Kodları":"Bağlantı Yenilendi","Pil":"0.5","Zaman":"03.07.2019 14:34:17","Enlem":"39.87425","Boylam":"32.86414","Hata":"0","Kaynak":"GPS","Rakım":"111","Son Adres Bilgisi ":"Ali Haydar Feroğlu Sk. Sancak Merkez Ankara / Türkiye     "},{"﻿Kutu Adı":"T01-0001","IMEI":"3.58021E+14","Olay Kodları":"Bağlantı Yenilendi","Pil":"0.5","Zaman":"03.07.2019 13:32:49","Enlem":"39.88033","Boylam":"32.87517","Hata":"0","Kaynak":"GPS","Rakım":"111","Son Adres Bilgisi ":"Çukurca Sitesi Birlik Merkez Ankara / Türkiye     "},{"﻿Kutu Adı":"T01-0001","IMEI":"3.58021E+14","Olay Kodları":"Bağlantı Yenilendi","Pil":"0.5","Zaman":"03.07.2019 12:28:53","Enlem":"39.87579","Boylam":"32.86398","Hata":"0","Kaynak":"GPS","Rakım":"1064","Son Adres Bilgisi ":"508. Cd. Sancak Merkez Ankara / Türkiye     "},{"﻿Kutu Adı":"T01-0001","IMEI":"3.58021E+14","Olay Kodları":"Bağlantı Yenilendi","Pil":"0.5","Zaman":"03.07.2019 11:26:23","Enlem":"39.87596","Boylam":"32.86424","Hata":"0","Kaynak":"GPS","Rakım":"1069","Son Adres Bilgisi ":"507. Sk. Sancak Merkez Ankara / Türkiye     "},{"﻿Kutu Adı":"T01-0001","IMEI":"3.58021E+14","Olay Kodları":"Bağlantı Yenilendi","Pil":"0.5","Zaman":"03.07.2019 10:24:05","Enlem":"39.8758","Boylam":"32.86406","Hata":"0","Kaynak":"GPS","Rakım":"1101","Son Adres Bilgisi ":"508. Cd. Sancak Merkez Ankara / Türkiye     "},{"﻿Kutu Adı":"T01-0001","IMEI":"3.58021E+14","Olay Kodları":"Bağlantı Yenilendi","Pil":"0.5","Zaman":"03.07.2019 09:23:08","Enlem":"39.87007","Boylam":"32.86606","Hata":"0","Kaynak":"GPS","Rakım":"111","Son Adres Bilgisi ":"549. Cd. Sancak Merkez Ankara / Türkiye     "},{"﻿Kutu Adı":"T01-0001","IMEI":"3.58021E+14","Olay Kodları":"Bağlantı Yenilendi","Pil":"0.55","Zaman":"03.07.2019 08:19:06","Enlem":"39.87586","Boylam":"32.86418","Hata":"0","Kaynak":"GPS","Rakım":"1053","Son Adres Bilgisi ":"507. Sk. Sancak Merkez Ankara / Türkiye     "},{"﻿Kutu Adı":"T01-0001","IMEI":"3.58021E+14","Olay Kodları":"Bağlantı Yenilendi","Pil":"0.55","Zaman":"03.07.2019 07:14:17","Enlem":"39.90743","Boylam":"32.88294","Hata":"0","Kaynak":"GPS","Rakım":"1008","Son Adres Bilgisi ":"Açın Cd. Aşıkpaşa Merkez Ankara / Türkiye     "},{"﻿Kutu Adı":"T01-0001","IMEI":"3.58021E+14","Olay Kodları":"Bağlantı Yenilendi","Pil":"0.55","Zaman":"03.07.2019 06:13:45","Enlem":"39.90763","Boylam":"32.88261","Hata":"0","Kaynak":"GPS","Rakım":"961","Son Adres Bilgisi ":"244. Cd. Aşıkpaşa Merkez Ankara / Türkiye     "},{"﻿Kutu Adı":"T01-0001","IMEI":"3.58021E+14","Olay Kodları":"Bağlantı Yenilendi","Pil":"0.55","Zaman":"03.07.2019 05:11:17","Enlem":"39.90762","Boylam":"32.88258","Hata":"0","Kaynak":"GPS","Rakım":"938","Son Adres Bilgisi ":"Vedat Dalokay Cd. Aşıkpaşa Merkez Ankara / Türkiye     "},{"﻿Kutu Adı":"T01-0001","IMEI":"3.58021E+14","Olay Kodları":"Bağlantı Yenilendi","Pil":"0.55","Zaman":"03.07.2019 04:09:47","Enlem":"39.90756","Boylam":"32.8826","Hata":"0","Kaynak":"GPS","Rakım":"932","Son Adres Bilgisi ":"Vedat Dalokay Cd. Aşıkpaşa Merkez Ankara / Türkiye     "},{"﻿Kutu Adı":"T01-0001","IMEI":"3.58021E+14","Olay Kodları":"Bağlantı Yenilendi","Pil":"0.55","Zaman":"03.07.2019 03:06:48","Enlem":"39.90657","Boylam":"32.88419","Hata":"0","Kaynak":"GPS","Rakım":"111","Son Adres Bilgisi ":"208. Sk. Aşıkpaşa Merkez Ankara / Türkiye     "},{"﻿Kutu Adı":"T01-0001","IMEI":"3.58021E+14","Olay Kodları":"Bağlantı Yenilendi","Pil":"0.55","Zaman":"03.07.2019 02:05:44","Enlem":"39.90759","Boylam":"32.88263","Hata":"0","Kaynak":"GPS","Rakım":"921","Son Adres Bilgisi ":"244. Cd. Aşıkpaşa Merkez Ankara / Türkiye     "},{"﻿Kutu Adı":"T01-0001","IMEI":"3.58021E+14","Olay Kodları":"Bağlantı Yenilendi","Pil":"0.55","Zaman":"03.07.2019 01:02:18","Enlem":"39.90718","Boylam":"32.87864","Hata":"0","Kaynak":"GPS","Rakım":"111","Son Adres Bilgisi ":"219. Sk. Metin Oktay Merkez Ankara / Türkiye     "},{"﻿Kutu Adı":"T01-0001","IMEI":"3.58021E+14","Olay Kodları":"Bağlantı Yenilendi","Pil":"0.55","Zaman":"02.07.2019 23:58:17","Enlem":"39.90769564","Boylam":"32.88246718","Hata":"140","Kaynak":"WIFI","Rakım":"0","Son Adres Bilgisi ":"Vedat Dalokay Cd. Aşıkpaşa Merkez Ankara / Türkiye     "},{"﻿Kutu Adı":"T01-0001","IMEI":"3.58021E+14","Olay Kodları":"Bağlantı Yenilendi","Pil":"0.55","Zaman":"02.07.2019 22:56:17","Enlem":"39.90762","Boylam":"32.88251","Hata":"0","Kaynak":"GPS","Rakım":"920","Son Adres Bilgisi ":"Vedat Dalokay Cd. Aşıkpaşa Merkez Ankara / Türkiye     "},{"﻿Kutu Adı":"T01-0001","IMEI":"3.58021E+14","Olay Kodları":"Bağlantı Yenilendi","Pil":"0.55","Zaman":"02.07.2019 21:53:46","Enlem":"39.90782","Boylam":"32.88231","Hata":"0","Kaynak":"GPS","Rakım":"939","Son Adres Bilgisi ":"Vedat Dalokay Cd. Aşıkpaşa Merkez Ankara / Türkiye     "},{"﻿Kutu Adı":"T01-0001","IMEI":"3.58021E+14","Olay Kodları":"Bağlantı Yenilendi","Pil":"0.55","Zaman":"02.07.2019 20:52:05","Enlem":"39.90753","Boylam":"32.88257","Hata":"0","Kaynak":"GPS","Rakım":"918","Son Adres Bilgisi ":"Vedat Dalokay Cd. Aşıkpaşa Merkez Ankara / Türkiye     "},{"﻿Kutu Adı":"T01-0001","IMEI":"3.58021E+14","Olay Kodları":"Bağlantı Yenilendi","Pil":"0.55","Zaman":"02.07.2019 19:50:39","Enlem":"39.90923","Boylam":"32.88791","Hata":"0","Kaynak":"GPS","Rakım":"111","Son Adres Bilgisi ":"430/1. Sk. Türközü Merkez Ankara / Türkiye     "},{"﻿Kutu Adı":"T01-0001","IMEI":"3.58021E+14","Olay Kodları":"Bağlantı Yenilendi","Pil":"0.55","Zaman":"02.07.2019 18:48:15","Enlem":"39.90815","Boylam":"32.87779","Hata":"0","Kaynak":"GPS","Rakım":"1232","Son Adres Bilgisi ":"Seyit Gazi Cd. Metin Oktay Merkez Ankara / Türkiye     "},{"﻿Kutu Adı":"T01-0001","IMEI":"3.58021E+14","Olay Kodları":"Bağlantı Yenilendi","Pil":"0.55","Zaman":"02.07.2019 17:43:25","Enlem":"39.87554","Boylam":"32.86418","Hata":"0","Kaynak":"GPS","Rakım":"1101","Son Adres Bilgisi ":"507. Sk. Sancak Merkez Ankara / Türkiye     "},{"﻿Kutu Adı":"T01-0001","IMEI":"3.58021E+14","Olay Kodları":"Bağlantı Yenilendi","Pil":"0.55","Zaman":"02.07.2019 16:38:16","Enlem":"39.87544","Boylam":"32.86453","Hata":"0","Kaynak":"GPS","Rakım":"1089","Son Adres Bilgisi ":"Ali Haydar Feroğlu Sk. Sancak Merkez Ankara / Türkiye     "},{"﻿Kutu Adı":"T01-0001","IMEI":"3.58021E+14","Olay Kodları":"Bağlantı Yenilendi","Pil":"0.55","Zaman":"02.07.2019 15:36:06","Enlem":"39.87564","Boylam":"32.86403","Hata":"0","Kaynak":"GPS","Rakım":"1067","Son Adres Bilgisi ":"507. Sk. Sancak Merkez Ankara / Türkiye     "},{"﻿Kutu Adı":"T01-0001","IMEI":"3.58021E+14","Olay Kodları":"Bağlantı Yenilendi","Pil":"0.55","Zaman":"02.07.2019 14:32:22","Enlem":"39.87636","Boylam":"32.86704","Hata":"0","Kaynak":"GPS","Rakım":"1478","Son Adres Bilgisi ":"428. Cd. Sancak Merkez Ankara / Türkiye     "},{"﻿Kutu Adı":"T01-0001","IMEI":"3.58021E+14","Olay Kodları":"Bağlantı Yenilendi","Pil":"0.55","Zaman":"02.07.2019 13:28:58","Enlem":"39.87568","Boylam":"32.8638","Hata":"0","Kaynak":"GPS","Rakım":"1061","Son Adres Bilgisi ":"508. Cd. Sancak Merkez Ankara / Türkiye     "},{"﻿Kutu Adı":"T01-0001","IMEI":"3.58021E+14","Olay Kodları":"Bağlantı Yenilendi","Pil":"0.55","Zaman":"02.07.2019 12:24:06","Enlem":"39.8753579","Boylam":"32.86379856","Hata":"125","Kaynak":"WIFI","Rakım":"0","Son Adres Bilgisi ":"507. Sk. Sancak Merkez Ankara / Türkiye     "},{"﻿Kutu Adı":"T01-0001","IMEI":"3.58021E+14","Olay Kodları":"Bağlantı Yenilendi","Pil":"0.55","Zaman":"02.07.2019 11:17:46","Enlem":"39.87572","Boylam":"32.86444","Hata":"0","Kaynak":"GPS","Rakım":"1155","Son Adres Bilgisi ":"508. Cd. Sancak Merkez Ankara / Türkiye     "},{"﻿Kutu Adı":"T01-0001","IMEI":"3.58021E+14","Olay Kodları":"Bağlantı Yenilendi","Pil":"0.55","Zaman":"02.07.2019 10:16:48","Enlem":"39.87443","Boylam":"32.85719","Hata":"0","Kaynak":"GPS","Rakım":"112","Son Adres Bilgisi ":"719. Sk. Yıldızevler Merkez Ankara / Türkiye     "},{"﻿Kutu Adı":"T01-0001","IMEI":"3.58021E+14","Olay Kodları":"Bağlantı Yenilendi","Pil":"0.55","Zaman":"02.07.2019 09:15:16","Enlem":"39.87546","Boylam":"32.86411","Hata":"0","Kaynak":"GPS","Rakım":"1081","Son Adres Bilgisi ":"507. Sk. Sancak Merkez Ankara / Türkiye     "},{"﻿Kutu Adı":"T01-0001","IMEI":"3.58021E+14","Olay Kodları":"Bağlantı Yenilendi","Pil":"0.55","Zaman":"02.07.2019 08:11:37","Enlem":"39.87550441","Boylam":"32.8639372","Hata":"70","Kaynak":"WIFI","Rakım":"0","Son Adres Bilgisi ":"507. Sk. Sancak Merkez Ankara / Türkiye     "},{"﻿Kutu Adı":"T01-0001","IMEI":"3.58021E+14","Olay Kodları":"Bağlantı Yenilendi","Pil":"0.55","Zaman":"02.07.2019 07:07:46","Enlem":"39.90776","Boylam":"32.88242","Hata":"0","Kaynak":"GPS","Rakım":"928","Son Adres Bilgisi ":"Vedat Dalokay Cd. Aşıkpaşa Merkez Ankara / Türkiye     "},{"﻿Kutu Adı":"T01-0001","IMEI":"3.58021E+14","Olay Kodları":"Bağlantı Yenilendi","Pil":"0.55","Zaman":"02.07.2019 06:05:47","Enlem":"39.90756","Boylam":"32.8826","Hata":"0","Kaynak":"GPS","Rakım":"942","Son Adres Bilgisi ":"Vedat Dalokay Cd. Aşıkpaşa Merkez Ankara / Türkiye     "},{"﻿Kutu Adı":"T01-0001","IMEI":"3.58021E+14","Olay Kodları":"Bağlantı Yenilendi","Pil":"0.55","Zaman":"02.07.2019 05:03:46","Enlem":"39.90786","Boylam":"32.88238","Hata":"0","Kaynak":"GPS","Rakım":"933","Son Adres Bilgisi ":"Vedat Dalokay Cd. Aşıkpaşa Merkez Ankara / Türkiye     "},{"﻿Kutu Adı":"T01-0001","IMEI":"3.58021E+14","Olay Kodları":"Bağlantı Yenilendi","Pil":"0.55","Zaman":"02.07.2019 04:02:14","Enlem":"39.90754","Boylam":"32.88253","Hata":"0","Kaynak":"GPS","Rakım":"0","Son Adres Bilgisi ":"Vedat Dalokay Cd. Aşıkpaşa Merkez Ankara / Türkiye     "},{"﻿Kutu Adı":"T01-0001","IMEI":"3.58021E+14","Olay Kodları":"Bağlantı Yenilendi","Pil":"0.55","Zaman":"02.07.2019 02:59:47","Enlem":"39.90765","Boylam":"32.8823","Hata":"0","Kaynak":"GPS","Rakım":"896","Son Adres Bilgisi ":"Vedat Dalokay Cd. Aşıkpaşa Merkez Ankara / Türkiye     "},{"﻿Kutu Adı":"T01-0001","IMEI":"3.58021E+14","Olay Kodları":"Bağlantı Yenilendi","Pil":"0.55","Zaman":"02.07.2019 01:59:14","Enlem":"39.90783","Boylam":"32.8823","Hata":"0","Kaynak":"GPS","Rakım":"919","Son Adres Bilgisi ":"Vedat Dalokay Cd. Aşıkpaşa Merkez Ankara / Türkiye     "},{"﻿Kutu Adı":"T01-0001","IMEI":"3.58021E+14","Olay Kodları":"Bağlantı Yenilendi","Pil":"0.55","Zaman":"02.07.2019 00:56:09","Enlem":"39.90318","Boylam":"32.88331","Hata":"0","Kaynak":"GPS","Rakım":"112","Son Adres Bilgisi ":"276. Sk. Bademlidere Merkez Ankara / Türkiye     "},{"﻿Kutu Adı":"T01-0001","IMEI":"3.58021E+14","Olay Kodları":"Bağlantı Yenilendi","Pil":"0.6","Zaman":"01.07.2019 23:52:40","Enlem":"39.90760852","Boylam":"32.88237339","Hata":"140","Kaynak":"WIFI","Rakım":"0","Son Adres Bilgisi ":"Vedat Dalokay Cd. Aşıkpaşa Merkez Ankara / Türkiye     "},{"﻿Kutu Adı":"T01-0001","IMEI":"3.58021E+14","Olay Kodları":"Bağlantı Yenilendi","Pil":"0.6","Zaman":"01.07.2019 22:51:16","Enlem":"39.90761","Boylam":"32.88255","Hata":"0","Kaynak":"GPS","Rakım":"942","Son Adres Bilgisi ":"Vedat Dalokay Cd. Aşıkpaşa Merkez Ankara / Türkiye     "},{"﻿Kutu Adı":"T01-0001","IMEI":"3.58021E+14","Olay Kodları":"Bağlantı Yenilendi","Pil":"0.6","Zaman":"01.07.2019 21:45:17","Enlem":"39.90749","Boylam":"32.88258","Hata":"0","Kaynak":"GPS","Rakım":"918","Son Adres Bilgisi ":"Vedat Dalokay Cd. Aşıkpaşa Merkez Ankara / Türkiye     "},{"﻿Kutu Adı":"T01-0001","IMEI":"3.58021E+14","Olay Kodları":"Bağlantı Yenilendi","Pil":"0.6","Zaman":"01.07.2019 20:42:46","Enlem":"39.90777","Boylam":"32.88236","Hata":"0","Kaynak":"GPS","Rakım":"926","Son Adres Bilgisi ":"Vedat Dalokay Cd. Aşıkpaşa Merkez Ankara / Türkiye     "},{"﻿Kutu Adı":"T01-0001","IMEI":"3.58021E+14","Olay Kodları":"Bağlantı Yenilendi","Pil":"0.6","Zaman":"01.07.2019 19:41:05","Enlem":"39.90781","Boylam":"32.88245","Hata":"0","Kaynak":"GPS","Rakım":"944","Son Adres Bilgisi ":"Vedat Dalokay Cd. Aşıkpaşa Merkez Ankara / Türkiye     "},{"﻿Kutu Adı":"T01-0001","IMEI":"3.58021E+14","Olay Kodları":"Bağlantı Yenilendi","Pil":"0.6","Zaman":"01.07.2019 18:38:18","Enlem":"39.90702","Boylam":"32.88072","Hata":"0","Kaynak":"GPS","Rakım":"111","Son Adres Bilgisi ":"214. Cd. Aşıkpaşa Merkez Ankara / Türkiye     "},{"﻿Kutu Adı":"T01-0001","IMEI":"3.58021E+14","Olay Kodları":"Bağlantı Yenilendi","Pil":"0.6","Zaman":"01.07.2019 17:33:06","Enlem":"39.87574914","Boylam":"32.86393325","Hata":"140","Kaynak":"WIFI","Rakım":"0","Son Adres Bilgisi ":"508. Cd. Sancak Merkez Ankara / Türkiye     "},{"﻿Kutu Adı":"T01-0001","IMEI":"3.58021E+14","Olay Kodları":"Bağlantı Yenilendi","Pil":"0.6","Zaman":"01.07.2019 16:25:31","Enlem":"39.87575205","Boylam":"32.86395058","Hata":"140","Kaynak":"WIFI","Rakım":"0","Son Adres Bilgisi ":"508. Cd. Sancak Merkez Ankara / Türkiye     "},{"﻿Kutu Adı":"T01-0001","IMEI":"3.58021E+14","Olay Kodları":"Bağlantı Yenilendi","Pil":"0.6","Zaman":"01.07.2019 15:24:27","Enlem":"39.87558779","Boylam":"32.86391046","Hata":"140","Kaynak":"WIFI","Rakım":"0","Son Adres Bilgisi ":"507. Sk. Sancak Merkez Ankara / Türkiye     "},{"﻿Kutu Adı":"T01-0001","IMEI":"3.58021E+14","Olay Kodları":"Bağlantı Yenilendi","Pil":"0.6","Zaman":"01.07.2019 14:23:37","Enlem":"39.87590733","Boylam":"32.86392426","Hata":"140","Kaynak":"WIFI","Rakım":"0","Son Adres Bilgisi ":"508. Cd. Sancak Merkez Ankara / Türkiye     "},{"﻿Kutu Adı":"T01-0001","IMEI":"3.58021E+14","Olay Kodları":"Bağlantı Yenilendi","Pil":"0.6","Zaman":"01.07.2019 13:22:52","Enlem":"39.87562168","Boylam":"32.86391623","Hata":"140","Kaynak":"WIFI","Rakım":"0","Son Adres Bilgisi ":"507. Sk. Sancak Merkez Ankara / Türkiye     "},{"﻿Kutu Adı":"T01-0001","IMEI":"3.58021E+14","Olay Kodları":"Bağlantı Yenilendi","Pil":"0.6","Zaman":"01.07.2019 12:21:38","Enlem":"39.87564989","Boylam":"32.8639133","Hata":"140","Kaynak":"WIFI","Rakım":"0","Son Adres Bilgisi ":"508. Cd. Sancak Merkez Ankara / Türkiye     "},{"﻿Kutu Adı":"T01-0001","IMEI":"3.58021E+14","Olay Kodları":"Bağlantı Yenilendi","Pil":"0.55","Zaman":"01.07.2019 11:20:03","Enlem":"39.8757028","Boylam":"32.86379324","Hata":"140","Kaynak":"WIFI","Rakım":"0","Son Adres Bilgisi ":"508. Cd. Sancak Merkez Ankara / Türkiye     "},{"﻿Kutu Adı":"T01-0001","IMEI":"3.58021E+14","Olay Kodları":"Bağlantı Yenilendi","Pil":"0.55","Zaman":"01.07.2019 10:19:02","Enlem":"39.8757665","Boylam":"32.86394881","Hata":"140","Kaynak":"WIFI","Rakım":"0","Son Adres Bilgisi ":"508. Cd. Sancak Merkez Ankara / Türkiye     "},{"﻿Kutu Adı":"T01-0001","IMEI":"3.58021E+14","Olay Kodları":"Bağlantı Yenilendi","Pil":"0.55","Zaman":"01.07.2019 09:18:28","Enlem":"39.87575767","Boylam":"32.86397517","Hata":"140","Kaynak":"WIFI","Rakım":"0","Son Adres Bilgisi ":"508. Cd. Sancak Merkez Ankara / Türkiye     "},{"﻿Kutu Adı":"T01-0001","IMEI":"3.58021E+14","Olay Kodları":"Bağlantı Yenilendi","Pil":"0.5","Zaman":"01.07.2019 08:17:08","Enlem":"39.87569604","Boylam":"32.86387634","Hata":"140","Kaynak":"WIFI","Rakım":"0","Son Adres Bilgisi ":"508. Cd. Sancak Merkez Ankara / Türkiye     "},{"﻿Kutu Adı":"T01-0001","IMEI":"3.58021E+14","Olay Kodları":"Bağlantı Yenilendi","Pil":"0.45","Zaman":"01.07.2019 07:11:46","Enlem":"39.90768","Boylam":"32.88248","Hata":"0","Kaynak":"GPS","Rakım":"926","Son Adres Bilgisi ":"Vedat Dalokay Cd. Aşıkpaşa Merkez Ankara / Türkiye     "},{"﻿Kutu Adı":"T01-0001","IMEI":"3.58021E+14","Olay Kodları":"Bağlantı Yenilendi","Pil":"0.45","Zaman":"01.07.2019 06:10:16","Enlem":"39.9076","Boylam":"32.8825","Hata":"0","Kaynak":"GPS","Rakım":"940","Son Adres Bilgisi ":"Vedat Dalokay Cd. Aşıkpaşa Merkez Ankara / Türkiye     "},{"﻿Kutu Adı":"T01-0001","IMEI":"3.58021E+14","Olay Kodları":"Bağlantı Yenilendi","Pil":"0.45","Zaman":"01.07.2019 05:06:46","Enlem":"39.90774","Boylam":"32.88244","Hata":"0","Kaynak":"GPS","Rakım":"932","Son Adres Bilgisi ":"Vedat Dalokay Cd. Aşıkpaşa Merkez Ankara / Türkiye     "},{"﻿Kutu Adı":"T01-0001","IMEI":"3.58021E+14","Olay Kodları":"Bağlantı Yenilendi","Pil":"0.45","Zaman":"01.07.2019 04:05:18","Enlem":"39.90803","Boylam":"32.88248","Hata":"0","Kaynak":"GPS","Rakım":"960","Son Adres Bilgisi ":"Vedat Dalokay Cd. Aşıkpaşa Merkez Ankara / Türkiye     "},{"﻿Kutu Adı":"T01-0001","IMEI":"3.58021E+14","Olay Kodları":"Bağlantı Yenilendi","Pil":"0.5","Zaman":"01.07.2019 03:01:46","Enlem":"39.90764","Boylam":"32.88252","Hata":"0","Kaynak":"GPS","Rakım":"911","Son Adres Bilgisi ":"Vedat Dalokay Cd. Aşıkpaşa Merkez Ankara / Türkiye     "},{"﻿Kutu Adı":"T01-0001","IMEI":"3.58021E+14","Olay Kodları":"Bağlantı Yenilendi","Pil":"0.5","Zaman":"01.07.2019 01:59:58","Enlem":"39.90764526","Boylam":"32.88234155","Hata":"145","Kaynak":"WIFI","Rakım":"0","Son Adres Bilgisi ":"Vedat Dalokay Cd. Aşıkpaşa Merkez Ankara / Türkiye     "},{"﻿Kutu Adı":"T01-0001","IMEI":"3.58021E+14","Olay Kodları":"Bağlantı Yenilendi","Pil":"0.45","Zaman":"01.07.2019 00:55:29","Enlem":"39.90763","Boylam":"32.88262","Hata":"0","Kaynak":"GPS","Rakım":"928","Son Adres Bilgisi ":"244. Cd. Aşıkpaşa Merkez Ankara / Türkiye     "}]